fahrplan/__init__.py
fahrplan/api.py
fahrplan/display.py
fahrplan/helpers.py
fahrplan/main.py
fahrplan/meta.py
fahrplan/parser.py
fahrplan-1.1.2.dist-info/AUTHORS
fahrplan-1.1.2.dist-info/LICENSE
fahrplan-1.1.2.dist-info/METADATA
fahrplan-1.1.2.dist-info/WHEEL
fahrplan-1.1.2.dist-info/entry_points.txt
fahrplan-1.1.2.dist-info/top_level.txt
fahrplan-1.1.2.dist-info/RECORD
