Metadata-Version: 2.1
Name: fahrplan
Version: 1.1.2
Summary: A SBB/CFF/FFS commandline based timetable client.
Home-page: https://github.com/dbrgn/fahrplan
Author: Danilo Bargen and contributors
Author-email: mail@dbrgn.ch
License: GPLv3
Keywords: fahrplan timetable sbb cff ffs public transport
Platform: UNKNOWN
Classifier: Development Status :: 5 - Production/Stable
Classifier: Environment :: Console
Classifier: License :: OSI Approved :: GNU General Public License (GPL)
Classifier: Natural Language :: English
Classifier: Natural Language :: German
Classifier: Natural Language :: French
Classifier: Natural Language :: Italian
Classifier: Operating System :: MacOS
Classifier: Operating System :: POSIX :: Linux
Classifier: Programming Language :: Python :: 3
Classifier: Programming Language :: Python :: 3.5
Classifier: Programming Language :: Python :: 3.6
Classifier: Programming Language :: Python :: 3.7
Classifier: Programming Language :: Python :: 3.8
Classifier: Topic :: Internet
Classifier: Topic :: Terminals
Requires-Dist: requests (<3,>=1)
Requires-Dist: python-dateutil (<3,>=2.1)
Requires-Dist: texttable (<2,>=0.8.6)
